CMakeLists.txt
MANIFEST.in
README.rst
requirements.txt
setup.py
windows_build.bat
src/.editorconfig
src/.gitignore
src/.gitkeep
src/.travis.yml
src/AUTHORS
src/CMakeLists.txt
src/CMakeSettings.json
src/INSTALL
src/LICENSE
src/Makefile.am
src/README.deploy.txt
src/README.md
src/README.windows.txt
src/appveyor.yml
src/autogen.sh
src/configure.ac
src/deployvw.bat
src/libvw.pc.in
src/libvw_c_wrapper.pc.in
src/mkdevdist.sh
src/R/example.yaml
src/R/rscripts_readme.md
src/R/examples/vw_example.R
src/R/examples/vw_example_2.R
src/R/r.vw/DESCRIPTION
src/R/r.vw/NAMESPACE
src/R/r.vw/R/dt2vw.R
src/R/r.vw/R/vw.R
src/R/r.vw/man/dt2vw.Rd
src/R/r.vw/man/vw.Rd
src/acinclude.d/ax_boost_base.m4
src/acinclude.d/ax_boost_program_options.m4
src/acinclude.d/ax_check_zlib.m4
src/acinclude.d/ax_cxx_compile_stdcxx_11.m4
src/acinclude.d/ax_pthread.m4
src/allreduce/CMakeLists.txt
src/allreduce/allreduce.h
src/allreduce/allreduce_sockets.cc
src/allreduce/allreduce_threads.cc
src/big_tests/HOWTO.use_it.txt
src/big_tests/HOWTO.write_new_tests.txt
src/big_tests/Makefile
src/big_tests/README.txt
src/big_tests/dataSets.mk
src/big_tests/testDetails.mk
src/big_tests/testGroups.mk
src/big_tests/expected/1a/err
src/big_tests/expected/1a/out
src/big_tests/expected/1b/err
src/big_tests/expected/1b/out
src/big_tests/expected/2/err
src/big_tests/expected/2/out
src/big_tests/expected/3/err
src/big_tests/expected/3/out
src/big_tests/expected/4a/err
src/big_tests/expected/4a/out
src/big_tests/expected/4b/err
src/big_tests/expected/4b/out
src/big_tests/expected/5a/err
src/big_tests/expected/5a/out
src/big_tests/expected/5b/err
src/big_tests/expected/5b/out
src/big_tests/expected/6a/err
src/big_tests/expected/6a/out
src/big_tests/expected/6b/err
src/big_tests/expected/6b/out
src/big_tests/testCode/URLRep.munge.sh
src/big_tests/testCode/covtype.munge.sh
src/big_tests/testCode/floatingTolerance.pl
src/big_tests/testCode/mnist.extract-labels.pl
src/big_tests/testCode/mnist.extractfeatures.cpp
vowpalwabbitds.egg-info/PKG-INFO
vowpalwabbitds.egg-info/SOURCES.txt
vowpalwabbitds.egg-info/dependency_links.txt
vowpalwabbitds.egg-info/not-zip-safe
vowpalwabbitds.egg-info/top_level.txt
